{"Ground truth": {"_type": "image-file", "path": "media/images/Ground truth_540_2b699b6dd104920bdd05.png", "sha256": "2b699b6dd104920bdd05171dc1a0607c52db61777939661415a65b2cb696e0a6", "size": 1032, "format": "png", "width": 256, "height": 256, "caption": "Top: Output, Bottom: Input"}, "Prediction": {"_type": "image-file", "path": "media/images/Prediction_540_f1ceec6094fa7b2178da.png", "sha256": "f1ceec6094fa7b2178daf46de27c396e0fd70756429957b3129cfe4b58136537", "size": 2143, "format": "png", "width": 256, "height": 256, "caption": "Top: Output, Bottom: Input"}, "_timestamp": 1649843381, "_runtime": 53, "_step": 541, "test_F1": 0.6662834286689758, "test_acc": 0.7607625126838684, "test_IoU": 0.4995691180229187, "test_Kappa": 1.2446410655975342, "_wandb": {"runtime": 54}}